Day6_shiftreg/src/shiftreg.v
module shiftreg #(parameter n = 8)(clk,rst_n,s_i,p_o);
    input clk,rst_n,s_i;
    output reg [n-1:0] p_o;

    reg [n-1:0] p_next;

    always @(posedge clk,negedge rst_n)
        begin
            if(!rst_n)
                p_o<=0;
            else
                p_o<=p_next;
        end
    
    assign p_next={s_i,p_o[n-1:1]};

endmodule

Day6_shiftreg/top.v
module top #(parameter n = 8)(clk,rst_n,s_i,p_o);
    input clk,rst_n,s_i;
    output reg [n-1:0] p_o;
    shiftreg #(.n(8)) shiftreg_inst (clk,rst_n,s_i,p_o);
endmodule

Day6_shiftreg/sim.v
module sim #(parameter n = 8)(clk,rst_n,s_i,p_o);
    input clk,rst_n,s_i;
    output reg [n-1:0] p_o;
    top #(.n(8)) dut (clk,rst_n,s_i,p_o);
    initial 
        begin
            $dumpfile("sim.vcd");
            $dumpvars(0,sim);
            #1;
        end
endmodule

Day6_shiftreg/Test/sim.vcd
$date
	Wed Jun 22 20:13:13 2022
$end
$version
	Icarus Verilog
$end
$timescale
	1ps
$end
$scope module sim $end
$var wire 1 ! clk $end
$var wire 1 " rst_n $end
$var wire 1 # s_i $end
$var wire 8 $ p_o [7:0] $end
$scope module dut $end
$var wire 1 ! clk $end
$var wire 1 " rst_n $end
$var wire 1 # s_i $end
$var wire 8 % p_o [7:0] $end
$scope module shiftreg_inst $end
$var wire 1 ! clk $end
$var wire 1 " rst_n $end
$var wire 1 # s_i $end
$var wire 8 & p_next [7:0] $end
$var reg 8 ' p_o [7:0] $end
$upscope $end
$upscope $end
$upscope $end
$enddefinitions $end
#0
$dumpvars
b0xxxxxxx '
b0xxxxxx &
b0xxxxxxx %
b0xxxxxxx $
0#
1"
1!
$end
#5000
0!
#10000
b0xxxxx &
b0xxxxxx $
b0xxxxxx %
b0xxxxxx '
1!
#15000
b0 &
b0 $
b0 %
b0 '
0"
0!
#20000
1!
#25000
0!
#30000
1!
#35000
1"
0!
#40000
1!
#45000
0!
#50000
1!
#55000
b10000000 &
1#
0!
#60000
b11000000 &
b10000000 $
b10000000 %
b10000000 '
1!
#65000
b1000000 &
0#
0!
#70000
b100000 &
b1000000 $
b1000000 %
b1000000 '
1!
#75000
b10100000 &
1#
0!
#80000
b11010000 &
b10100000 $
b10100000 %
b10100000 '
1!
#85000
0!
#90000
b11101000 &
b11010000 $
b11010000 %
b11010000 '
1!
#95000
0!
#100000
b11110100 &
b11101000 $
b11101000 %
b11101000 '
1!
#105000
0!
#110000
b11111010 &
b11110100 $
b11110100 %
b11110100 '
1!
#115000
0!
#120000
b11111101 &
b11111010 $
b11111010 %
b11111010 '
1!
#125000
0!
#130000
b11111110 &
b11111101 $
b11111101 %
b11111101 '
1!
#135000
b1111110 &
0#
0!
#140000
b111111 &
b1111110 $
b1111110 %
b1111110 '
1!
#145000
0!
#150000
b11111 &
b111111 $
b111111 %
b111111 '
1!
#155000
0!
#160000
b1111 &
b11111 $
b11111 %
b11111 '
1!
#165000
b10001111 &
1#
0!
#170000
b11000111 &
b10001111 $
b10001111 %
b10001111 '
1!
#175000
b1000111 &
0#
0!
#180000
b100011 &
b1000111 $
b1000111 %
b1000111 '
1!
#185000
0!
#190000
b10001 &
b100011 $
b100011 %
b100011 '
1!
#195000
b10010001 &
1#
0!
#200000
b11001000 &
b10010001 $
b10010001 %
b10010001 '
1!
#205000
b1001000 &
0#
0!
#210000
b100100 &
b1001000 $
b1001000 %
b1001000 '
1!
#215000
0!
#220000
b10010 &
b100100 $
b100100 %
b100100 '
1!
#225000
0!
#230000
b1001 &
b10010 $
b10010 %
b10010 '
1!
#235000
b10001001 &
1#
0!
#240000
b11000100 &
b10001001 $
b10001001 %
b10001001 '
1!
#245000
0!
#250000
b11100010 &
b11000100 $
b11000100 %
b11000100 '
1!
#255000
0!
#260000
b11110001 &
b11100010 $
b11100010 %
b11100010 '
1!
#265000
b1110001 &
0#
0!
#270000
b111000 &
b1110001 $
b1110001 %
b1110001 '
1!
#275000
0!
#280000
b11100 &
b111000 $
b111000 %
b111000 '
1!
#285000
b10011100 &
1#
0!
#290000
b11001110 &
b10011100 $
b10011100 %
b10011100 '
1!
#295000
b1001110 &
0#
0!
#300000
b100111 &
b1001110 $
b1001110 %
b1001110 '
1!
#305000
b10100111 &
1#
0!
#310000
b11010011 &
b10100111 $
b10100111 %
b10100111 '
1!
#315000
0!
#320000
b11101001 &
b11010011 $
b11010011 %
b11010011 '
1!
#325000
0!
#330000
b11110100 &
b11101001 $
b11101001 %
b11101001 '
1!
#335000
b1110100 &
0#
0!
#340000
b111010 &
b1110100 $
b1110100 %
b1110100 '
1!
#345000
b10111010 &
1#
0!
#350000
b11011101 &
b10111010 $
b10111010 %
b10111010 '
1!
#355000
0!
#360000
b11101110 &
b11011101 $
b11011101 %
b11011101 '
1!
#365000
0!
#370000
b11110111 &
b11101110 $
b11101110 %
b11101110 '
1!
#375000
b1110111 &
0#
0!
#380000
b111011 &
b1110111 $
b1110111 %
b1110111 '
1!
#385000
b10111011 &
1#
0!
#390000
b11011101 &
b10111011 $
b10111011 %
b10111011 '
1!
#395000
b1011101 &
0#
0!
#400000
b101110 &
b1011101 $
b1011101 %
b1011101 '
1!
#405000
b10101110 &
1#
0!
#410000
b11010111 &
b10101110 $
b10101110 %
b10101110 '
1!
#415000
b1010111 &
0#
0!
#420000
b101011 &
b1010111 $
b1010111 %
b1010111 '
1!
#425000
0!
#430000
b10101 &
b101011 $
b101011 %
b101011 '
1!
#435000
b10010101 &
1#
0!
#440000
b11001010 &
b10010101 $
b10010101 %
b10010101 '
1!
#445000
b1001010 &
0#
0!
#450000
b100101 &
b1001010 $
b1001010 %
b1001010 '
1!
#455000
b10100101 &
1#
0!
#460000
b11010010 &
b10100101 $
b10100101 %
b10100101 '
1!
#465000
b1010010 &
0#
0!
#470000
b101001 &
b1010010 $
b1010010 %
b1010010 '
1!
#475000
b10101001 &
1#
0!
#480000
b11010100 &
b10101001 $
b10101001 %
b10101001 '
1!
#485000
b1010100 &
0#
0!
#490000
b101010 &
b1010100 $
b1010100 %
b1010100 '
1!
#495000
0!
#500000
b10101 &
b101010 $
b101010 %
b101010 '
1!
#505000
0!
#510000
b1010 &
b10101 $
b10101 %
b10101 '
1!
#515000
0!
#520000
b101 &
b1010 $
b1010 %
b1010 '
1!
#525000
b10000101 &
1#
0!
#530000
b11000010 &
b10000101 $
b10000101 %
b10000101 '
1!
#535000
b1000010 &
0#
0!
#540000
b100001 &
b1000010 $
b1000010 %
b1000010 '
1!
#545000
0!
#550000
b10000 &
b100001 $
b100001 %
b100001 '
1!
#555000
0!
#560000
b1000 &
b10000 $
b10000 %
b10000 '
1!
#565000
b10001000 &
1#
0!
#570000
b11000100 &
b10001000 $
b10001000 %
b10001000 '
1!
#575000
0!
#580000
b11100010 &
b11000100 $
b11000100 %
b11000100 '
1!
#585000
b1100010 &
0#
0!
#590000
b110001 &
b1100010 $
b1100010 %
b1100010 '
1!
#595000
b10110001 &
1#
0!
#600000
b11011000 &
b10110001 $
b10110001 %
b10110001 '
1!
#605000
0!
#610000
b11101100 &
b11011000 $
b11011000 %
b11011000 '
1!
#615000
0!
#620000
b11110110 &
b11101100 $
b11101100 %
b11101100 '
1!
#625000
0!
#630000
b11111011 &
b11110110 $
b11110110 %
b11110110 '
1!
#635000
b1111011 &
0#
0!
#640000
b111101 &
b1111011 $
b1111011 %
b1111011 '
1!
#645000
0!
#650000
b11110 &
b111101 $
b111101 %
b111101 '
1!
#655000
0!
#660000
b1111 &
b11110 $
b11110 %
b11110 '
1!
#665000
0!
#670000
b111 &
b1111 $
b1111 %
b1111 '
1!
#675000
0!
#680000
b11 &
b111 $
b111 %
b111 '
1!
#685000
b10000011 &
1#
0!
#690000
b11000001 &
b10000011 $
b10000011 %
b10000011 '
1!
#695000
0!
#700000
b11100000 &
b11000001 $
b11000001 %
b11000001 '
1!
#705000
b1100000 &
0#
0!
#710000
b110000 &
b1100000 $
b1100000 %
b1100000 '
1!
#715000
b10110000 &
1#
0!
#720000
b11011000 &
b10110000 $
b10110000 %
b10110000 '
1!
#725000
b1011000 &
0#
0!
#730000
b101100 &
b1011000 $
b1011000 %
b1011000 '
1!
#735000
0!
#740000
b10110 &
b101100 $
b101100 %
b101100 '
1!
#745000
0!
#750000
b1011 &
b10110 $
b10110 %
b10110 '
1!
#755000
b10001011 &
1#
0!
#760000
b11000101 &
b10001011 $
b10001011 %
b10001011 '
1!
#765000
b1000101 &
0#
0!
#770000
b100010 &
b1000101 $
b1000101 %
b1000101 '
1!
#775000
b10100010 &
1#
0!
#780000
b11010001 &
b10100010 $
b10100010 %
b10100010 '
1!
#785000
b1010001 &
0#
0!
#790000
b101000 &
b1010001 $
b1010001 %
b1010001 '
1!
#795000
b10101000 &
1#
0!
#800000
b11010100 &
b10101000 $
b10101000 %
b10101000 '
1!
#805000
b1010100 &
0#
0!
#810000
b101010 &
b1010100 $
b1010100 %
b1010100 '
1!
#815000
b10101010 &
1#
0!
#820000
b11010101 &
b10101010 $
b10101010 %
b10101010 '
1!
#825000
b1010101 &
0#
0!
#830000
b101010 &
b1010101 $
b1010101 %
b1010101 '
1!
#835000
0!
#840000
b10101 &
b101010 $
b101010 %
b101010 '
1!
#845000
b10010101 &
1#
0!
#850000
b11001010 &
b10010101 $
b10010101 %
b10010101 '
1!
#855000
b1001010 &
0#
0!
#860000
b100101 &
b1001010 $
b1001010 %
b1001010 '
1!
#865000
b10100101 &
1#
0!
#870000
b11010010 &
b10100101 $
b10100101 %
b10100101 '
1!
#875000
0!
#880000
b11101001 &
b11010010 $
b11010010 %
b11010010 '
1!
#885000
b1101001 &
0#
0!
#890000
b110100 &
b1101001 $
b1101001 %
b1101001 '
1!
#895000
0!
#900000
b11010 &
b110100 $
b110100 %
b110100 '
1!
#905000
0!
#910000
b1101 &
b11010 $
b11010 %
b11010 '
1!
#915000
b10001101 &
1#
0!
#920000
b11000110 &
b10001101 $
b10001101 %
b10001101 '
1!
#925000
b1000110 &
0#
0!
#930000
b100011 &
b1000110 $
b1000110 %
b1000110 '
1!
#935000
b10100011 &
1#
0!
#940000
b11010001 &
b10100011 $
b10100011 %
b10100011 '
1!
#945000
0!
#950000
b11101000 &
b11010001 $
b11010001 %
b11010001 '
1!
#955000
0!
#960000
b11110100 &
b11101000 $
b11101000 %
b11101000 '
1!
#965000
b1110100 &
0#
0!
#970000
b111010 &
b1110100 $
b1110100 %
b1110100 '
1!
#975000
b10111010 &
1#
0!
#980000
b11011101 &
b10111010 $
b10111010 %
b10111010 '
1!
#985000
0!
#990000
b11101110 &
b11011101 $
b11011101 %
b11011101 '
1!
#995000
0!
#1000000
b11110111 &
b11101110 $
b11101110 %
b11101110 '
1!
#1005000
0!
#1010000
b11111011 &
b11110111 $
b11110111 %
b11110111 '
1!
#1015000
b1111011 &
0#
0!
#1020000
b111101 &
b1111011 $
b1111011 %
b1111011 '
1!
#1025000
0!
#1030000
b11110 &
b111101 $
b111101 %
b111101 '
1!
#1035000
0!
#1040000
b1111 &
b11110 $
b11110 %
b11110 '
1!
#1045000
0!
#1050000
b111 &
b1111 $
b1111 %
b1111 '
1!
#1055000
0!
#1060000
b11 &
b111 $
b111 %
b111 '
1!
#1065000
b10000011 &
1#
0!
#1070000
b11000001 &
b10000011 $
b10000011 %
b10000011 '
1!
#1075000
0!
#1080000
b11100000 &
b11000001 $
b11000001 %
b11000001 '
1!
#1085000
0!
#1090000
b11110000 &
b11100000 $
b11100000 %
b11100000 '
1!
#1095000
0!
#1100000
b11111000 &
b11110000 $
b11110000 %
b11110000 '
1!
#1105000
b1111000 &
0#
0!
#1110000
b111100 &
b1111000 $
b1111000 %
b1111000 '
1!
#1115000
0!
#1120000
b11110 &
b111100 $
b111100 %
b111100 '
1!
#1125000
b10011110 &
1#
0!
#1130000
b11001111 &
b10011110 $
b10011110 %
b10011110 '
1!
#1135000
b1001111 &
0#
0!
#1140000
b100111 &
b1001111 $
b1001111 %
b1001111 '
1!
#1145000
0!
#1150000
b10011 &
b100111 $
b100111 %
b100111 '
1!
#1155000
b10010011 &
1#
0!
#1160000
b11001001 &
b10010011 $
b10010011 %
b10010011 '
1!
#1165000
0!
#1170000
b11100100 &
b11001001 $
b11001001 %
b11001001 '
1!
#1175000
b1100100 &
0#
0!
#1180000
b110010 &
b1100100 $
b1100100 %
b1100100 '
1!
#1185000
0!
#1190000
b11001 &
b110010 $
b110010 %
b110010 '
1!
#1195000
0!
#1200000
b1100 &
b11001 $
b11001 %
b11001 '
1!
#1205000
0!
#1210000
b110 &
b1100 $
b1100 %
b1100 '
1!
#1215000
0!
#1220000
b11 &
b110 $
b110 %
b110 '
1!
#1225000
0!
#1230000
b1 &
b11 $
b11 %
b11 '
1!
#1235000
0!
#1240000
b0 &
b1 $
b1 %
b1 '
1!
#1245000
b10000000 &
1#
0!
#1250000
b11000000 &
b10000000 $
b10000000 %
b10000000 '
1!
#1255000
0!
#1260000
b11100000 &
b11000000 $
b11000000 %
b11000000 '
1!
#1265000
0!
#1270000
b11110000 &
b11100000 $
b11100000 %
b11100000 '
1!
#1275000
0!
#1280000
b11111000 &
b11110000 $
b11110000 %
b11110000 '
1!
#1285000
0!
#1290000
b11111100 &
b11111000 $
b11111000 %
b11111000 '
1!
#1295000
b1111100 &
0#
0!
#1300000
b111110 &
b1111100 $
b1111100 %
b1111100 '
1!
#1305000
0!
#1310000
b11111 &
b111110 $
b111110 %
b111110 '
1!
#1315000
b10011111 &
1#
0!
#1320000
b11001111 &
b10011111 $
b10011111 %
b10011111 '
1!
#1325000
b1001111 &
0#
0!
#1330000
b100111 &
b1001111 $
b1001111 %
b1001111 '
1!
#1335000
0!
#1340000
b10011 &
b100111 $
b100111 %
b100111 '
1!
#1345000
b10010011 &
1#
0!
#1350000
b11001001 &
b10010011 $
b10010011 %
b10010011 '
1!
#1355000
0!
#1360000
b11100100 &
b11001001 $
b11001001 %
b11001001 '
1!
#1365000
b1100100 &
0#
0!
#1370000
b110010 &
b1100100 $
b1100100 %
b1100100 '
1!
#1375000
0!
#1380000
b11001 &
b110010 $
b110010 %
b110010 '
1!
#1385000
b10011001 &
1#
0!
#1390000
b11001100 &
b10011001 $
b10011001 %
b10011001 '
1!
#1395000
b1001100 &
0#
0!
#1400000
b100110 &
b1001100 $
b1001100 %
b1001100 '
1!
#1405000
0!
#1410000
b10011 &
b100110 $
b100110 %
b100110 '
1!
#1415000
0!
#1420000
b1001 &
b10011 $
b10011 %
b10011 '
1!
#1425000
0!
#1430000
b100 &
b1001 $
b1001 %
b1001 '
1!
#1435000
0!
#1440000
b10 &
b100 $
b100 %
b100 '
1!
#1445000
0!
#1450000
b1 &
b10 $
b10 %
b10 '
1!
#1455000
0!
#1460000
b0 &
b1 $
b1 %
b1 '
1!
#1465000
b10000000 &
1#
0!
#1470000
b11000000 &
b10000000 $
b10000000 %
b10000000 '
1!
#1475000
b1000000 &
0#
0!
#1480000
b100000 &
b1000000 $
b1000000 %
b1000000 '
1!
#1485000
b10100000 &
1#
0!
#1490000
b11010000 &
b10100000 $
b10100000 %
b10100000 '
1!
#1495000
b1010000 &
0#
0!
#1500000
b101000 &
b1010000 $
b1010000 %
b1010000 '
1!
#1505000
b10101000 &
1#
0!
#1510000
b11010100 &
b10101000 $
b10101000 %
b10101000 '
1!
#1515000
0!
#1520000
b11101010 &
b11010100 $
b11010100 %
b11010100 '
1!
#1525000
b1101010 &
0#
0!
#1530000
b110101 &
b1101010 $
b1101010 %
b1101010 '
1!
#1535000
0!
#1540000
b11010 &
b110101 $
b110101 %
b110101 '
1!
#1545000
0!
#1550000
b1101 &
b11010 $
b11010 %
b11010 '
1!
#1555000
0!
#1560000
b110 &
b1101 $
b1101 %
b1101 '
1!
#1565000
b10000110 &
1#
0!
#1570000
b11000011 &
b10000110 $
b10000110 %
b10000110 '
1!
#1575000
0!
#1580000
b11100001 &
b11000011 $
b11000011 %
b11000011 '
1!
#1585000
0!
#1590000
b11110000 &
b11100001 $
b11100001 %
b11100001 '
1!
#1595000
b1110000 &
0#
0!
#1600000
b111000 &
b1110000 $
b1110000 %
b1110000 '
1!
#1605000
b10111000 &
1#
0!
#1610000
b11011100 &
b10111000 $
b10111000 %
b10111000 '
1!
#1615000
b1011100 &
0#
0!
#1620000
b101110 &
b1011100 $
b1011100 %
b1011100 '
1!
#1625000
0!
#1630000
b10111 &
b101110 $
b101110 %
b101110 '
1!
#1635000
b10010111 &
1#
0!
#1640000
b11001011 &
b10010111 $
b10010111 %
b10010111 '
1!
#1645000
b1001011 &
0#
0!
#1650000
b100101 &
b1001011 $
b1001011 %
b1001011 '
1!
#1655000
0!
#1660000
b10010 &
b100101 $
b100101 %
b100101 '
1!
#1665000
b10010010 &
1#
0!
#1670000
b11001001 &
b10010010 $
b10010010 %
b10010010 '
1!
#1675000
0!
#1680000
b11100100 &
b11001001 $
b11001001 %
b11001001 '
1!
#1685000
0!
#1690000
b11110010 &
b11100100 $
b11100100 %
b11100100 '
1!
#1695000
b1110010 &
0#
0!
#1700000
b111001 &
b1110010 $
b1110010 %
b1110010 '
1!
#1705000
b10111001 &
1#
0!
#1710000
b11011100 &
b10111001 $
b10111001 %
b10111001 '
1!
#1715000
b1011100 &
0#
0!
#1720000
b101110 &
b1011100 $
b1011100 %
b1011100 '
1!
#1725000
b10101110 &
1#
0!
#1730000
b11010111 &
b10101110 $
b10101110 %
b10101110 '
1!
#1735000
b1010111 &
0#
0!
#1740000
b101011 &
b1010111 $
b1010111 %
b1010111 '
1!
#1745000
b10101011 &
1#
0!
#1750000
b11010101 &
b10101011 $
b10101011 %
b10101011 '
1!
#1755000
b1010101 &
0#
0!
#1760000
b101010 &
b1010101 $
b1010101 %
b1010101 '
1!
#1765000
0!
#1770000
b10101 &
b101010 $
b101010 %
b101010 '
1!
#1775000
0!
#1780000
b1010 &
b10101 $
b10101 %
b10101 '
1!
#1785000
b10001010 &
1#
0!
#1790000
b11000101 &
b10001010 $
b10001010 %
b10001010 '
1!
#1795000
b1000101 &
0#
0!
#1800000
b100010 &
b1000101 $
b1000101 %
b1000101 '
1!
#1805000
b10100010 &
1#
0!
#1810000
b11010001 &
b10100010 $
b10100010 %
b10100010 '
1!
#1815000
b1010001 &
0#
0!
#1820000
b101000 &
b1010001 $
b1010001 %
b1010001 '
1!
#1825000
0!
#1830000
b10100 &
b101000 $
b101000 %
b101000 '
1!
#1835000
b10010100 &
1#
0!
#1840000
b11001010 &
b10010100 $
b10010100 %
b10010100 '
1!
#1845000
0!
#1850000
b11100101 &
b11001010 $
b11001010 %
b11001010 '
1!
#1855000
0!
#1860000
b11110010 &
b11100101 $
b11100101 %
b11100101 '
1!
#1865000
0!
#1870000
b11111001 &
b11110010 $
b11110010 %
b11110010 '
1!
#1875000
b1111001 &
0#
0!
#1880000
b111100 &
b1111001 $
b1111001 %
b1111001 '
1!
#1885000
0!
#1890000
b11110 &
b111100 $
b111100 %
b111100 '
1!
#1895000
0!
#1900000
b1111 &
b11110 $
b11110 %
b11110 '
1!
#1905000
b10001111 &
1#
0!
#1910000
b11000111 &
b10001111 $
b10001111 %
b10001111 '
1!
#1915000
0!
#1920000
b11100011 &
b11000111 $
b11000111 %
b11000111 '
1!
#1925000
b1100011 &
0#
0!
#1930000
b110001 &
b1100011 $
b1100011 %
b1100011 '
1!
#1935000
b10110001 &
1#
0!
#1940000
b11011000 &
b10110001 $
b10110001 %
b10110001 '
1!
#1945000
0!
#1950000
b11101100 &
b11011000 $
b11011000 %
b11011000 '
1!
#1955000
0!
#1960000
b11110110 &
b11101100 $
b11101100 %
b11101100 '
1!
#1965000
0!
#1970000
b11111011 &
b11110110 $
b11110110 %
b11110110 '
1!
#1975000
0!
#1980000
b11111101 &
b11111011 $
b11111011 %
b11111011 '
1!
#1985000
0!
#1990000
b11111110 &
b11111101 $
b11111101 %
b11111101 '
1!
#1995000
b1111110 &
0#
0!
#2000000
b111111 &
b1111110 $
b1111110 %
b1111110 '
1!
#2005000
0!
#2010000
b11111 &
b111111 $
b111111 %
b111111 '
1!
#2015000
0!
#2020000
b1111 &
b11111 $
b11111 %
b11111 '
1!
#2025000
0!
#2030000
b111 &
b1111 $
b1111 %
b1111 '
1!
#2035000
b10000111 &
1#
0!
#2040000
b11000011 &
b10000111 $
b10000111 %
b10000111 '
1!
#2045000
b1000011 &
0#
0!
#2050000
b100001 &
b1000011 $
b1000011 %
b1000011 '
1!
#2055000
b10100001 &
1#
0!
#2060000
b11010000 &
b10100001 $
b10100001 %
b10100001 '
1!
#2065000
b1010000 &
0#
0!
#2070000
b101000 &
b1010000 $
b1010000 %
b1010000 '
1!
#2075000
b10101000 &
1#
0!
#2080000
b11010100 &
b10101000 $
b10101000 %
b10101000 '
1!
#2085000
0!
#2090000
b11101010 &
b11010100 $
b11010100 %
b11010100 '
1!
#2095000
0!
#2100000
b11110101 &
b11101010 $
b11101010 %
b11101010 '
1!
#2105000
b1110101 &
0#
0!
#2110000
b111010 &
b1110101 $
b1110101 %
b1110101 '
1!
#2115000
b10111010 &
1#
0!
#2120000
b11011101 &
b10111010 $
b10111010 %
b10111010 '
1!
#2125000
b1011101 &
0#
0!
#2130000
b101110 &
b1011101 $
b1011101 %
b1011101 '
1!
#2135000
0!
#2140000
b10111 &
b101110 $
b101110 %
b101110 '
1!
#2145000
0!
#2150000
b1011 &
b10111 $
b10111 %
b10111 '
1!
#2155000
0!
#2160000
b101 &
b1011 $
b1011 %
b1011 '
1!
#2165000
b10000101 &
1#
0!
#2170000
b11000010 &
b10000101 $
b10000101 %
b10000101 '
1!
#2175000
b1000010 &
0#
0!
#2180000
b100001 &
b1000010 $
b1000010 %
b1000010 '
1!
#2185000
b10100001 &
1#
0!
#2190000
b11010000 &
b10100001 $
b10100001 %
b10100001 '
1!
#2195000
0!
#2200000
b11101000 &
b11010000 $
b11010000 %
b11010000 '
1!
#2205000
0!
#2210000
b11110100 &
b11101000 $
b11101000 %
b11101000 '
1!
#2215000
b1110100 &
0#
0!
#2220000
b111010 &
b1110100 $
b1110100 %
b1110100 '
1!
#2225000
0!
#2230000
b11101 &
b111010 $
b111010 %
b111010 '
1!
#2235000
b10011101 &
1#
0!
#2240000
b11001110 &
b10011101 $
b10011101 %
b10011101 '
1!
#2245000
b1001110 &
0#
0!
#2250000
b100111 &
b1001110 $
b1001110 %
b1001110 '
1!
#2255000
b10100111 &
1#
0!
#2260000
b11010011 &
b10100111 $
b10100111 %
b10100111 '
1!
#2265000
0!
#2270000
b11101001 &
b11010011 $
b11010011 %
b11010011 '
1!
#2275000
0!
#2280000
b11110100 &
b11101001 $
b11101001 %
b11101001 '
1!
#2285000
b1110100 &
0#
0!
#2290000
b111010 &
b1110100 $
b1110100 %
b1110100 '
1!
#2295000
b10111010 &
1#
0!
#2300000
b11011101 &
b10111010 $
b10111010 %
b10111010 '
1!
#2305000
b1011101 &
0#
0!
#2310000
b101110 &
b1011101 $
b1011101 %
b1011101 '
1!
#2315000
b10101110 &
1#
0!
#2320000
b11010111 &
b10101110 $
b10101110 %
b10101110 '
1!
#2325000
b1010111 &
0#
0!
#2330000
b101011 &
b1010111 $
b1010111 %
b1010111 '
1!
#2335000
b10101011 &
1#
0!
#2340000
b11010101 &
b10101011 $
b10101011 %
b10101011 '
1!
#2345000
b1010101 &
0#
0!
#2350000
b101010 &
b1010101 $
b1010101 %
b1010101 '
1!
#2355000
0!
#2360000
b10101 &
b101010 $
b101010 %
b101010 '
1!
#2365000
b10010101 &
1#
0!
#2370000
b11001010 &
b10010101 $
b10010101 %
b10010101 '
1!
#2375000
b1001010 &
0#
0!
#2380000
b100101 &
b1001010 $
b1001010 %
b1001010 '
1!
#2385000
0!
#2390000
b10010 &
b100101 $
b100101 %
b100101 '
1!
#2395000
b10010010 &
1#
0!
#2400000
b11001001 &
b10010010 $
b10010010 %
b10010010 '
1!
#2405000
0!
#2410000
b11100100 &
b11001001 $
b11001001 %
b11001001 '
1!
#2415000
0!
#2420000
b11110010 &
b11100100 $
b11100100 %
b11100100 '
1!
#2425000
0!
#2430000
b11111001 &
b11110010 $
b11110010 %
b11110010 '
1!
#2435000
0!
#2440000
b11111100 &
b11111001 $
b11111001 %
b11111001 '
1!
#2445000
0!
#2450000
b11111110 &
b11111100 $
b11111100 %
b11111100 '
1!
#2455000
b1111110 &
0#
0!
#2460000
b111111 &
b1111110 $
b1111110 %
b1111110 '
1!
#2465000
0!
#2470000
b11111 &
b111111 $
b111111 %
b111111 '
1!
#2475000
0!
#2480000
b1111 &
b11111 $
b11111 %
b11111 '
1!
#2485000
0!
#2490000
b111 &
b1111 $
b1111 %
b1111 '
1!
#2495000
0!
#2500000
b11 &
b111 $
b111 %
b111 '
1!
#2505000
0!
#2510000
b1 &
b11 $
b11 %
b11 '
1!
#2515000
0!
#2520000
b0 &
b1 $
b1 %
b1 '
1!
#2525000
0!
#2530000
b0 $
b0 %
b0 '
1!
#2535000
0!
#2540000
1!
#2545000
0!
#2550000
1!
#2555000
b10000000 &
1#
0!
#2560000
b11000000 &
b10000000 $
b10000000 %
b10000000 '
1!
#2565000
0!
#2570000
b11100000 &
b11000000 $
b11000000 %
b11000000 '
1!
#2575000
b1100000 &
0#
0!
#2580000
b110000 &
b1100000 $
b1100000 %
b1100000 '
1!
#2585000
b10110000 &
1#
0!
#2590000
b11011000 &
b10110000 $
b10110000 %
b10110000 '
1!
#2595000
b1011000 &
0#
0!
#2600000
b101100 &
b1011000 $
b1011000 %
b1011000 '
1!
#2605000
b10101100 &
1#
0!
#2610000
b11010110 &
b10101100 $
b10101100 %
b10101100 '
1!
#2615000
0!
#2620000
b11101011 &
b11010110 $
b11010110 %
b11010110 '
1!
#2625000
b1101011 &
0#
0!
#2630000
b110101 &
b1101011 $
b1101011 %
b1101011 '
1!
#2635000
0!
#2640000
b11010 &
b110101 $
b110101 %
b110101 '
1!
#2645000
0!
#2650000
b1101 &
b11010 $
b11010 %
b11010 '
1!
#2655000
0!
#2660000
b110 &
b1101 $
b1101 %
b1101 '
1!
#2665000
0!
#2670000
b11 &
b110 $
b110 %
b110 '
1!
#2675000
0!
#2680000
b1 &
b11 $
b11 %
b11 '
1!
#2685000
b10000001 &
1#
0!
#2690000
b11000000 &
b10000001 $
b10000001 %
b10000001 '
1!
#2695000
b1000000 &
0#
0!
#2700000
b100000 &
b1000000 $
b1000000 %
b1000000 '
1!
#2705000
0!
#2710000
b10000 &
b100000 $
b100000 %
b100000 '
1!
#2715000
b10010000 &
1#
0!
#2720000
b11001000 &
b10010000 $
b10010000 %
b10010000 '
1!
#2725000
b1001000 &
0#
0!
#2730000
b100100 &
b1001000 $
b1001000 %
b1001000 '
1!
#2735000
0!
#2740000
b10010 &
b100100 $
b100100 %
b100100 '
1!
#2745000
0!
#2750000
b1001 &
b10010 $
b10010 %
b10010 '
1!
#2755000
b10001001 &
1#
0!
#2760000
b11000100 &
b10001001 $
b10001001 %
b10001001 '
1!
#2765000
b1000100 &
0#
0!
#2770000
b100010 &
b1000100 $
b1000100 %
b1000100 '
1!
#2775000
0!
#2780000
b10001 &
b100010 $
b100010 %
b100010 '
1!
#2785000
0!
#2790000
b1000 &
b10001 $
b10001 %
b10001 '
1!
#2795000
0!
#2800000
b100 &
b1000 $
b1000 %
b1000 '
1!
#2805000
b10000100 &
1#
0!
#2810000
b11000010 &
b10000100 $
b10000100 %
b10000100 '
1!
#2815000
0!
#2820000
b11100001 &
b11000010 $
b11000010 %
b11000010 '
1!
#2825000
0!
#2830000
b11110000 &
b11100001 $
b11100001 %
b11100001 '
1!
#2835000
b1110000 &
0#
0!
#2840000
b111000 &
b1110000 $
b1110000 %
b1110000 '
1!
#2845000
b10111000 &
1#
0!
#2850000
b11011100 &
b10111000 $
b10111000 %
b10111000 '
1!
#2855000
0!
#2860000
b11101110 &
b11011100 $
b11011100 %
b11011100 '
1!
#2865000
0!
#2870000
b11110111 &
b11101110 $
b11101110 %
b11101110 '
1!
#2875000
b1110111 &
0#
0!
#2880000
b111011 &
b1110111 $
b1110111 %
b1110111 '
1!
#2885000
b10111011 &
1#
0!
#2890000
b11011101 &
b10111011 $
b10111011 %
b10111011 '
1!
#2895000
b1011101 &
0#
0!
#2900000
b101110 &
b1011101 $
b1011101 %
b1011101 '
1!
#2905000
0!
#2910000
b10111 &
b101110 $
b101110 %
b101110 '
1!
#2915000
0!
#2920000
b1011 &
b10111 $
b10111 %
b10111 '
1!
#2925000
0!
#2930000
b101 &
b1011 $
b1011 %
b1011 '
1!
#2935000
0!
#2940000
b10 &
b101 $
b101 %
b101 '
1!
#2945000
b10000010 &
1#
0!
#2950000
b11000001 &
b10000010 $
b10000010 %
b10000010 '
1!
#2955000
b1000001 &
0#
0!
#2960000
b100000 &
b1000001 $
b1000001 %
b1000001 '
1!
#2965000
b10100000 &
1#
0!
#2970000
b11010000 &
b10100000 $
b10100000 %
b10100000 '
1!
#2975000
b1010000 &
0#
0!
#2980000
b101000 &
b1010000 $
b1010000 %
b1010000 '
1!
#2985000
0!
#2990000
b10100 &
b101000 $
b101000 %
b101000 '
1!
#2995000
b10010100 &
1#
0!
#3000000
b11001010 &
b10010100 $
b10010100 %
b10010100 '
1!
#3005000
b1001010 &
0#
0!
#3010000
b100101 &
b1001010 $
b1001010 %
b1001010 '
1!
#3015000
b10100101 &
1#
0!
#3020000
b11010010 &
b10100101 $
b10100101 %
b10100101 '
1!
#3025000
0!
#3030000
b11101001 &
b11010010 $
b11010010 %
b11010010 '
1!
#3035000
b1101001 &
0#
0!
#3040000
b110100 &
b1101001 $
b1101001 %
b1101001 '
1!
#3045000
b10110100 &
1#
0!
#3050000
b11011010 &
b10110100 $
b10110100 %
b10110100 '
1!
