trianglewave/trianglewave.v
module  trianglewave 
       #(parameter min = 0, parameter max = 7, parameter nbits=3)
       (clk,rst_n,count);
       input clk,rst_n;
       output reg [nbits-1:0] count;

       reg [nbits-1:0] count_next;
       reg down, down_next;

       always @(posedge clk,negedge rst_n)
              begin
                     if(!rst_n)
                          count<=0;
                     else
                          count<=count_next;
              end

       always @(*)
              begin
                     if(down==0)
                            count_next=count+1;
                     else
                            count_next=count-1;
              end

       always @(posedge clk,negedge rst_n)
              begin
                     if(!rst_n)
                         down<=0;
                     else
                         down<=down_next;   
              end
       
       always @(*)
              begin
                     if(down==0)
                            begin
                                   down_next=0;
                                   if(count==max-1)
                                          down_next=1;
                            end
                     else
                            begin
                                   down_next=1;
                                   if(count==min+1)
                                          down_next=0;
                            end
              end

       initial 
              begin
                     $dumpfile("trianglewave.vcd");
                     $dumpvars(0,trianglewave);
              end
endmodule

trianglewave/Test/trianglewave.vcd
$date
	Wed Jun 15 10:54:34 2022
$end
$version
	Icarus Verilog
$end
$timescale
	1ps
$end
$scope module trianglewave $end
$var wire 1 ! clk $end
$var wire 1 " rst_n $end
$var reg 3 # count [2:0] $end
$var reg 3 $ count_next [2:0] $end
$var reg 1 % down $end
$var reg 1 & down_next $end
$upscope $end
$enddefinitions $end
#0
$dumpvars
x&
x%
bx $
bx #
1"
1!
$end
#5000
0&
b1 $
0%
b0 #
0"
0!
#10000
1!
#15000
1"
0!
#20000
b10 $
b1 #
1!
#25000
0!
#30000
b11 $
b10 #
1!
#35000
0!
#40000
b100 $
b11 #
1!
#45000
0!
#50000
b101 $
b100 #
1!
#55000
0!
#60000
b110 $
b101 #
1!
#65000
0!
#70000
1&
b111 $
b110 #
1!
#75000
0!
#80000
b110 $
1%
b111 #
1!
#85000
0!
#90000
b101 $
b110 #
1!
#95000
0!
#100000
b100 $
b101 #
1!
#105000
0!
#110000
b11 $
b100 #
1!
#115000
0!
#120000
b10 $
b11 #
1!
#125000
0!
#130000
b1 $
b10 #
1!
#135000
0!
#140000
b0 $
0&
b1 #
1!
#145000
0!
#150000
b1 $
b0 #
0%
1!
#155000
0!
#160000
b10 $
b1 #
1!
#165000
0!
#170000
b11 $
b10 #
1!
#175000
0!
#180000
b100 $
b11 #
1!
#185000
0!
#190000
b101 $
b100 #
1!
#195000
0!
#200000
b110 $
b101 #
1!
#205000
0!
#210000
1&
b111 $
b110 #
1!
#215000
0!
#220000
b110 $
1%
b111 #
1!
#225000
0!
#230000
b101 $
b110 #
1!
#235000
0!
#240000
b100 $
b101 #
1!
#245000
0!
#250000
b11 $
b100 #
1!
#255000
0!
#260000
b10 $
b11 #
1!
#265000
0!
#270000
b1 $
b10 #
1!
#275000
0!
#280000
b0 $
0&
b1 #
1!
#285000
0!
#290000
b1 $
b0 #
0%
1!
#295000
0!
#300000
b10 $
b1 #
1!
#305000
0!
#310000
b11 $
b10 #
1!
#315000
0!
#320000
b100 $
b11 #
1!
#325000
0!
#330000
b101 $
b100 #
1!
#335000
0!
#340000
b110 $
b101 #
1!
#345000
0!
#350000
1&
b111 $
b110 #
1!
#355000
0!
#360000
b110 $
1%
b111 #
1!
#365000
0!
#370000
b101 $
b110 #
1!
#375000
0!
#380000
b100 $
b101 #
1!
#385000
0!
#390000
b11 $
b100 #
1!
#395000
0!
#400000
b10 $
b11 #
1!
#405000
0!
#410000
b1 $
b10 #
1!
#415000
0!
#420000
b0 $
0&
b1 #
1!
#425000
0!
#430000
b1 $
b0 #
0%
1!
#435000
0!
#440000
b10 $
b1 #
1!
#445000
0!
#450000
b11 $
b10 #
1!
#455000
0!
#460000
b100 $
b11 #
1!
#465000
0!
#470000
b101 $
b100 #
1!
#475000
0!
#480000
b110 $
b101 #
1!
#485000
0!
#490000
1&
b111 $
b110 #
1!
#495000
0!
#500000
b110 $
1%
b111 #
1!
#505000
0!
#510000
b101 $
b110 #
1!
#515000
0!
#520000
b100 $
b101 #
1!
#525000
0!
#530000
b11 $
b100 #
1!
#535000
0!
#540000
b10 $
b11 #
1!
#545000
0!
#550000
b1 $
b10 #
1!
#555000
0!
#560000
b0 $
0&
b1 #
1!
#565000
0!
#570000
b1 $
b0 #
0%
1!
#575000
0!
#580000
b10 $
b1 #
1!
#585000
0!
#590000
b11 $
b10 #
1!
#595000
0!
#600000
b100 $
b11 #
1!
#605000
0!
#610000
b101 $
b100 #
1!
#615000
0!
#620000
b110 $
b101 #
1!
#625000
0!
#630000
1&
b111 $
b110 #
1!
#635000
0!
#640000
b110 $
1%
b111 #
1!
#645000
0!
#650000
b101 $
b110 #
1!
#655000
0!
#660000
b100 $
b101 #
1!
#665000
0!
#670000
b11 $
b100 #
1!
#675000
0!
#680000
b10 $
b11 #
1!
#685000
0!
#690000
b1 $
b10 #
1!
#695000
0!
#700000
b0 $
0&
b1 #
1!
#705000
0!
#710000
b1 $
b0 #
0%
1!
#715000
0!
#720000
b10 $
b1 #
1!
#725000
0!
#730000
b11 $
b10 #
1!
#735000
0!
#740000
b100 $
b11 #
1!
#745000
0!
#750000
b101 $
b100 #
1!
#755000
0!
#760000
b110 $
b101 #
1!
#765000
0!
#770000
1&
b111 $
b110 #
1!
#775000
0!
#780000
b110 $
1%
b111 #
1!
#785000
0!
#790000
b101 $
b110 #
1!
#795000
0!
#800000
b100 $
b101 #
1!
#805000
0!
#810000
b11 $
b100 #
1!
#815000
0!
#820000
b10 $
b11 #
1!
#825000
0!
#830000
b1 $
b10 #
1!
#835000
0!
#840000
b0 $
0&
b1 #
1!
#845000
0!
#850000
b1 $
b0 #
0%
1!
#855000
0!
#860000
b10 $
b1 #
1!
#865000
0!
#870000
b11 $
b10 #
1!
#875000
0!
#880000
b100 $
b11 #
1!
#885000
0!
#890000
b101 $
b100 #
1!
#895000
0!
#900000
b110 $
b101 #
1!
#905000
0!
#910000
1&
b111 $
b110 #
1!
#915000
0!
#920000
b110 $
1%
b111 #
1!
#925000
0!
#930000
b101 $
b110 #
1!
#935000
0!
#940000
b100 $
b101 #
1!
#945000
0!
#950000
b11 $
b100 #
1!
#955000
0!
#960000
b10 $
b11 #
1!
#965000
0!
#970000
b1 $
b10 #
1!
#975000
0!
#980000
b0 $
0&
b1 #
1!
#985000
0!
#990000
b1 $
b0 #
0%
1!
#995000
0!
#1000000
b10 $
b1 #
1!
#1005000
0!
#1010000
b11 $
b10 #
1!
