Day2_dff/dff.v
module dff(clk,rst_n,d,q_no_rst,q_syn_rst,q_asyn_rst);
       input clk,rst_n,d;
       output reg q_no_rst,q_syn_rst,q_asyn_rst;
       
       //no reset
       always @(posedge clk) 
              begin
                     q_no_rst<=d;
              end

       //asyn reset
       always @(posedge clk,negedge rst_n) 
              begin
                     if(!rst_n)
                            q_asyn_rst<=0;
                     else
                            q_asyn_rst<=d;
              end

       //sync reset
       always @(posedge clk) 
              begin
                     if(!rst_n)
                            q_syn_rst<=0;
                     else
                            q_syn_rst<=d;
              end

       initial 
              begin
                     $dumpfile("dff.vcd");
                     $dumpvars(0,dff);
              end
endmodule

Day2_dff/Test/dff.vcd
$date
	Tue Jun 14 19:39:32 2022
$end
$version
	Icarus Verilog
$end
$timescale
	1ps
$end
$scope module dff $end
$var wire 1 ! clk $end
$var wire 1 " d $end
$var wire 1 # rst_n $end
$var reg 1 $ q_asyn_rst $end
$var reg 1 % q_no_rst $end
$var reg 1 & q_syn_rst $end
$upscope $end
$enddefinitions $end
#0
$dumpvars
z&
z%
z$
1#
z"
1!
$end
#5000
1"
0!
#10000
1&
1%
1$
1!
#15000
0!
#20000
1!
#25000
0!
#30000
1!
#34000
0$
0#
#35000
0"
0!
#40000
0%
0&
1!
#45000
0!
#50000
1!
#55000
0!
#60000
1!
#65000
0!
#70000
1!
#75000
0!
#80000
1!
#85000
0!
#90000
1!
#95000
0!
#100000
1!
#105000
0!
#110000
1!
#115000
1"
1#
0!
#120000
1%
1&
1$
1!
#125000
0!
#130000
1!
#135000
0!
#140000
1!
#145000
0!
#150000
1!
#155000
0!
#160000
1!
#162000
0$
0#
#165000
0"
0!
#170000
0&
0%
1!
#175000
0!
#180000
1!
#185000
0!
#190000
1!
#195000
1"
0!
#200000
1%
1!
#205000
0!
#210000
1!
#215000
0!
#220000
1!
#225000
0!
#230000
1!
#235000
0!
#240000
1!
#245000
0!
#250000
1!
#255000
0!
#260000
1!
#265000
0!
#268000
1#
#270000
1&
1$
1!
#275000
0"
0!
#280000
0%
0&
0$
1!
#285000
0!
#290000
1!
#295000
0!
#300000
1!
#305000
0!
#310000
1!
#312000
0#
#315000
0!
#320000
1!
#325000
0!
#330000
1!
#335000
0!
#340000
1!
#345000
1"
1#
0!
#350000
1&
1%
1$
1!
#355000
0!
#360000
1!
#365000
0!
#370000
1!
#375000
0!
#380000
1!
#385000
0!
#390000
1!
#395000
0!
#400000
1!
#405000
0!
#410000
1!
#415000
0!
#420000
1!
#421000
0$
0#
#425000
0"
0!
#430000
0&
0%
1!
#435000
0!
#440000
1!
#445000
0!
#450000
1!
#455000
0!
#460000
1!
#465000
0!
#470000
1!
#475000
0!
#480000
1!
#485000
0!
#490000
1!
#495000
0!
#500000
1!
#505000
0!
#510000
1!
#515000
0!
#520000
1!
#525000
1"
0!
#530000
1%
1!
#535000
0!
#540000
1!
#545000
0!
#546000
1#
#550000
1&
1$
1!
#555000
0"
0!
#560000
0%
0&
0$
1!
#565000
0!
#570000
1!
#575000
1"
0!
#580000
1%
1&
1$
1!
#585000
0!
#590000
1!
#595000
0!
#599000
0$
0#
#600000
0&
1!
#605000
0!
#610000
1!
#615000
0!
#620000
1!
#625000
0!
#630000
1!
#635000
0"
0!
#640000
0%
1!
#645000
0!
#650000
1!
#655000
0!
#660000
1!
#663000
1#
#665000
0!
#670000
1!
#675000
0!
#680000
1!
#685000
0!
#690000
1!
#695000
0!
#700000
1!
#705000
0!
#710000
1!
#715000
0!
#720000
1!
#725000
0!
#726000
0#
#730000
1!
#735000
0!
#740000
1!
#745000
0!
#750000
1!
#755000
0!
#760000
1!
#765000
0!
#770000
1#
1!
#775000
1"
0!
#780000
1%
1&
1$
1!
#785000
0!
#790000
1!
#795000
0!
#800000
1!
#805000
0!
#810000
1!
#815000
0!
#820000
1!
#825000
0!
#830000
1!
#835000
0!
#840000
1!
#845000
0"
0!
#850000
0&
0%
0$
1!
#855000
0!
#860000
1!
#865000
0!
#870000
1!
#874000
0#
#875000
1"
0!
#880000
1%
1!
#885000
0!
#890000
1!
#895000
0!
#900000
1!
#905000
0!
#910000
1!
#915000
0!
#920000
1!
#925000
0!
#930000
1!
#935000
0!
#940000
1!
#945000
0!
#950000
1!
#955000
0!
#960000
1!
#965000
0!
#970000
1!
#974000
1#
#975000
0!
#980000
1&
1$
1!
#985000
0!
#990000
1!
#995000
0!
#1000000
1!
#1005000
0!
#1010000
1!
#1015000
0"
0!
#1020000
0%
0&
0$
1!
#1025000
0!
#1030000
1!
#1035000
0!
#1040000
1!
#1045000
0!
#1050000
1!
#1055000
1"
0!
#1060000
1%
1&
1$
1!
#1065000
0!
#1070000
1!
#1075000
0!
#1080000
1!
#1085000
0!
#1090000
1!
#1095000
0!
#1100000
1!
#1105000
0!
#1106000
0$
0#
#1110000
0&
1!
#1115000
0"
0!
#1120000
0%
1!
#1125000
0!
#1130000
1!
#1135000
0!
#1140000
1!
#1142000
1#
#1145000
1"
0!
#1150000
1&
1%
1$
1!
#1155000
0!
#1160000
1!
#1165000
0!
#1170000
1!
#1175000
0!
#1180000
1!
#1185000
0"
0!
#1190000
0&
0%
0$
1!
#1195000
0!
#1200000
1!
#1205000
0!
#1210000
1!
#1213000
0#
#1215000
0!
#1220000
1!
#1225000
0!
#1230000
1!
#1235000
0!
#1240000
1!
#1245000
0!
#1247000
1#
#1250000
1!
#1255000
0!
#1260000
1!
#1265000
0!
#1270000
1!
#1275000
0!
#1278000
0#
#1280000
1!
#1285000
1"
0!
#1290000
1%
1!
#1295000
0!
#1300000
1!
#1305000
0!
#1310000
1!
#1312000
1#
#1315000
0!
#1320000
1&
1$
1!
#1325000
0!
#1330000
1!
#1335000
0!
#1340000
0&
0$
0#
1!
#1345000
0!
#1350000
1!
#1355000
0!
#1360000
1!
#1365000
0!
#1370000
1!
#1371000
1#
#1375000
0"
0!
#1380000
0%
1!
#1385000
0!
#1390000
1!
#1395000
0!
#1398000
0#
#1400000
1!
#1405000
0!
#1410000
1!
#1415000
0!
#1420000
1!
#1425000
0!
#1430000
1!
#1435000
0!
#1440000
1!
#1445000
0!
#1450000
1!
#1455000
0!
#1460000
1!
#1465000
1"
0!
#1470000
1%
1!
#1475000
0!
#1480000
1!
#1485000
0!
#1490000
1!
#1495000
0!
#1500000
1!
#1505000
0!
#1510000
1!
#1515000
0!
#1520000
1!
#1525000
0!
#1530000
1!
#1535000
0!
#1540000
1!
#1545000
0!
#1550000
1!
#1555000
0!
#1560000
1!
#1565000
0"
0!
#1570000
0%
1!
#1575000
0!
#1580000
1!
#1585000
0!
#1590000
1!
#1595000
0!
#1600000
1!
#1605000
0!
#1610000
1!
#1615000
0!
#1620000
1#
1!
#1625000
0!
#1630000
1!
#1635000
0!
#1640000
1!
#1645000
0!
#1650000
1!
#1655000
0!
#1658000
0#
#1660000
1!
#1665000
0!
#1670000
1!
#1675000
0!
#1680000
1!
#1685000
0!
#1686000
1#
#1690000
1!
#1695000
1"
0!
#1700000
1%
1&
1$
1!
#1705000
0!
#1710000
1!
#1715000
0!
#1720000
1!
#1725000
0!
#1730000
1!
#1735000
0"
0!
#1740000
0%
0&
0$
1!
#1745000
0!
#1750000
1!
#1755000
0!
#1760000
1!
#1765000
1"
0!
#1770000
1&
1%
1$
1!
#1775000
0!
#1780000
1!
#1785000
0!
#1790000
1!
#1795000
0!
#1800000
1!
#1805000
0!
#1810000
1!
#1815000
0!
#1820000
1!
#1822000
0$
0#
#1825000
0"
0!
#1830000
0&
0%
1!
#1835000
0!
#1840000
1!
#1845000
0!
#1850000
1!
#1855000
0!
#1860000
1!
#1865000
0!
#1870000
1!
#1875000
0!
#1880000
1!
#1885000
0!
#1890000
1!
#1895000
0!
#1900000
1!
#1905000
0!
#1910000
1!
#1915000
0!
#1920000
1!
#1925000
1"
0!
#1930000
1%
1!
#1935000
0!
#1940000
1!
#1945000
0!
#1950000
1!
#1955000
0!
#1960000
1!
#1965000
0!
#1970000
1!
#1975000
0!
#1980000
1!
#1985000
0!
#1990000
1!
#1994000
1#
#1995000
0"
0!
#2000000
0%
1!
#2005000
0!
#2010000
1!
#2015000
0!
#2020000
1!
#2025000
0!
#2030000
1!
#2035000
0!
#2040000
1!
#2045000
0!
#2047000
0#
#2050000
1!
#2055000
0!
#2060000
1!
#2065000
0!
#2070000
1!
#2075000
0!
#2077000
1#
#2080000
1!
#2085000
1"
0!
#2090000
1&
1%
1$
1!
#2095000
0!
#2100000
1!
#2105000
0!
#2110000
1!
#2114000
0$
0#
#2115000
0"
0!
#2120000
0%
0&
1!
#2125000
0!
#2130000
1!
#2135000
0!
#2140000
1!
#2145000
1"
0!
#2150000
1%
1!
#2155000
0!
#2160000
1!
#2165000
0!
#2170000
1!
#2175000
0!
#2180000
1!
#2185000
0!
#2190000
1!
#2195000
0!
#2200000
1&
1$
1#
1!
#2205000
0"
0!
#2210000
0&
0%
0$
1!
#2215000
0!
#2220000
1!
#2225000
0#
0!
#2230000
1!
#2235000
0!
#2240000
1!
#2245000
0!
#2250000
1!
#2255000
0!
#2260000
1!
#2265000
0!
#2270000
1!
#2275000
0!
#2280000
1!
#2285000
0!
#2286000
1#
#2290000
1!
#2295000
1"
0!
#2300000
1%
1&
1$
1!
#2305000
0!
#2310000
1!
#2315000
0!
#2320000
1!
#2321000
0$
0#
#2325000
0!
#2330000
0&
1!
#2335000
0!
#2340000
1!
#2345000
0!
#2346000
1#
#2350000
1&
1$
1!
#2355000
0"
0!
#2360000
0%
0&
0$
1!
#2365000
0!
#2370000
1!
#2375000
0!
#2380000
1!
#2385000
0!
#2390000
1!
#2395000
1"
0!
#2400000
1%
1&
1$
1!
#2405000
0!
#2410000
1!
#2415000
0!
#2420000
1!
#2425000
0!
#2430000
1!
#2435000
0!
#2440000
1!
#2445000
0!
#2450000
1!
#2455000
0!
#2460000
1!
#2465000
0!
#2469000
0$
0#
#2470000
0&
1!
#2475000
0!
#2480000
1!
#2485000
0!
#2490000
1!
#2495000
0!
#2498000
1#
#2500000
1&
1$
1!
#2505000
0!
#2510000
1!
#2515000
0!
#2520000
1!
#2525000
0!
#2530000
1!
#2535000
0!
#2540000
1!
#2545000
0"
0!
#2550000
0&
0%
0$
1!
#2555000
0!
#2560000
1!
#2565000
0!
#2570000
1!
#2575000
1"
0!
#2580000
1%
1&
1$
1!
#2585000
0!
#2590000
1!
#2595000
0!
#2600000
1!
#2605000
0"
0$
0#
0!
#2610000
0&
0%
1!
#2615000
0!
#2620000
1!
#2625000
0!
#2630000
1!
#2635000
0!
#2640000
1!
#2641000
1#
#2645000
0!
#2650000
1!
#2655000
0!
#2660000
1!
#2665000
0!
#2670000
1!
#2675000
0!
#2680000
1!
#2685000
1"
0!
#2690000
1&
1%
1$
1!
#2695000
0!
#2700000
1!
#2705000
0!
#2710000
1!
#2715000
0"
0!
#2720000
0%
0&
0$
1!
#2725000
0!
#2730000
1!
#2735000
0!
#2737000
0#
#2740000
1!
#2745000
1"
0!
#2750000
1%
1!
#2755000
0!
#2760000
1!
#2765000
0!
#2770000
1!
#2771000
1#
#2775000
0!
#2780000
1&
1$
1!
#2785000
0!
#2790000
1!
#2795000
0!
#2796000
0$
0#
#2800000
0&
1!
#2805000
0!
#2810000
1!
#2815000
0!
#2820000
1!
#2825000
0!
#2830000
1!
#2835000
0!
#2840000
1!
#2845000
0"
0!
#2850000
0%
1!
#2855000
0!
#2860000
1!
#2865000
0!
#2870000
1!
#2874000
1#
#2875000
0!
#2880000
1!
#2885000
0!
#2890000
1!
#2895000
0!
#2900000
1!
#2905000
0!
#2910000
1!
#2915000
0!
#2920000
1!
#2925000
0!
#2930000
1!
#2935000
0!
#2940000
1!
#2945000
1"
0!
#2950000
1&
1%
1$
1!
#2955000
0!
#2960000
1!
#2965000
0!
#2970000
1!
#2975000
0!
#2980000
1!
#2985000
0!
#2990000
1!
#2995000
0!
#3000000
1!
#3005000
0!
#3010000
1!
#3015000
0"
0!
#3020000
0%
0&
0$
1!
#3025000
0!
#3030000
1!
#3035000
0!
#3040000
1!
#3045000
0!
#3050000
1!
#3055000
0!
#3060000
1!
#3065000
0!
#3070000
1!
#3075000
0!
#3080000
1!
#3085000
0!
#3086000
0#
#3090000
1!
#3095000
0!
#3100000
1!
#3105000
0!
#3110000
1!
#3115000
0!
#3120000
1!
#3125000
0!
#3130000
1!
#3135000
0!
#3140000
1!
#3145000
0!
#3150000
1!
#3155000
0!
#3160000
1!
#3165000
0!
#3170000
1!
#3175000
0!
#3178000
1#
#3180000
1!
#3185000
0!
#3190000
1!
#3195000
0!
#3200000
1!
#3205000
0!
#3210000
1!
#3212000
0#
#3215000
1"
0!
#3220000
1%
1!
